{
  "uid" : "40dc5c2d907eae8",
  "name" : "C658711_Verify_cust_param_lang",
  "title" : "Verify custom parameter lang",
  "time" : {
    "start" : 1590514035376,
    "stop" : 1590514040149,
    "duration" : 4773
  },
  "summary" : {
    "attachments" : 0,
    "steps" : 50
  },
  "failure" : null,
  "description" : null,
  "severity" : "NORMAL",
  "status" : "PASSED",
  "suite" : {
    "uid" : "138976ceb7006b19",
    "name" : "Suite : Test",
    "title" : "Suite : Test"
  },
  "steps" : [ {
    "name" : "logStep[Verifing :iu=%2F7646%2Fapp_android_us%2Fdb_display%2Fhome_screen%2Fhourly Pub Ad Call custParamlang]",
    "title" : "Verifing :iu=%2F7646%2Fapp_android_us%2Fdb_display%2Fhome_screen%2Fhourly Pub Ad Call custParamlang",
    "time" : {
      "start" : 1590514035805,
      "stop" : 1590514035805,
      "duration" : 0
    },
    "summary" : {
      "attachments" : 0,
      "steps" : 0
    },
    "status" : "PASSED",
    "attachments" : [ ],
    "steps" : [ ]
  }, {
    "name" : "logStep[Expected lang value : en]",
    "title" : "Expected lang value : en",
    "time" : {
      "start" : 1590514035944,
      "stop" : 1590514035944,
      "duration" : 0
    },
    "summary" : {
      "attachments" : 0,
      "steps" : 0
    },
    "status" : "PASSED",
    "attachments" : [ ],
    "steps" : [ ]
  }, {
    "name" : "logStep[PubAd lang value : en]",
    "title" : "PubAd lang value : en",
    "time" : {
      "start" : 1590514035944,
      "stop" : 1590514035944,
      "duration" : 0
    },
    "summary" : {
      "attachments" : 0,
      "steps" : 0
    },
    "status" : "PASSED",
    "attachments" : [ ],
    "steps" : [ ]
  }, {
    "name" : "logStep[lang value is matched with : en====en]",
    "title" : "lang value is matched with : en====en",
    "time" : {
      "start" : 1590514035944,
      "stop" : 1590514035944,
      "duration" : 0
    },
    "summary" : {
      "attachments" : 0,
      "steps" : 0
    },
    "status" : "PASSED",
    "attachments" : [ ],
    "steps" : [ ]
  }, {
    "name" : "logStep[Result Pass]",
    "title" : "Result Pass",
    "time" : {
      "start" : 1590514035944,
      "stop" : 1590514035944,
      "duration" : 0
    },
    "summary" : {
      "attachments" : 0,
      "steps" : 0
    },
    "status" : "PASSED",
    "attachments" : [ ],
    "steps" : [ ]
  }, {
    "name" : "logStep[Verifing :iu=%2F7646%2Fapp_android_us%2Fdb_display%2Fhome_screen%2Fmarquee Pub Ad Call custParamlang]",
    "title" : "Verifing :iu=%2F7646%2Fapp_android_us%2Fdb_display%2Fhome_screen%2Fmarquee Pub Ad Call custParamlang",
    "time" : {
      "start" : 1590514036133,
      "stop" : 1590514036133,
      "duration" : 0
    },
    "summary" : {
      "attachments" : 0,
      "steps" : 0
    },
    "status" : "PASSED",
    "attachments" : [ ],
    "steps" : [ ]
  }, {
    "name" : "logStep[Expected lang value : en]",
    "title" : "Expected lang value : en",
    "time" : {
      "start" : 1590514036271,
      "stop" : 1590514036271,
      "duration" : 0
    },
    "summary" : {
      "attachments" : 0,
      "steps" : 0
    },
    "status" : "PASSED",
    "attachments" : [ ],
    "steps" : [ ]
  }, {
    "name" : "logStep[PubAd lang value : en]",
    "title" : "PubAd lang value : en",
    "time" : {
      "start" : 1590514036271,
      "stop" : 1590514036271,
      "duration" : 0
    },
    "summary" : {
      "attachments" : 0,
      "steps" : 0
    },
    "status" : "PASSED",
    "attachments" : [ ],
    "steps" : [ ]
  }, {
    "name" : "logStep[lang value is matched with : en====en]",
    "title" : "lang value is matched with : en====en",
    "time" : {
      "start" : 1590514036271,
      "stop" : 1590514036271,
      "duration" : 0
    },
    "summary" : {
      "attachments" : 0,
      "steps" : 0
    },
    "status" : "PASSED",
    "attachments" : [ ],
    "steps" : [ ]
  }, {
    "name" : "logStep[Result Pass]",
    "title" : "Result Pass",
    "time" : {
      "start" : 1590514036271,
      "stop" : 1590514036271,
      "duration" : 0
    },
    "summary" : {
      "attachments" : 0,
      "steps" : 0
    },
    "status" : "PASSED",
    "attachments" : [ ],
    "steps" : [ ]
  }, {
    "name" : "logStep[Verifing :iu=%2F7646%2Fapp_android_us%2Fdb_display%2Fcard%2Fradar Pub Ad Call custParamlang]",
    "title" : "Verifing :iu=%2F7646%2Fapp_android_us%2Fdb_display%2Fcard%2Fradar Pub Ad Call custParamlang",
    "time" : {
      "start" : 1590514036807,
      "stop" : 1590514036807,
      "duration" : 0
    },
    "summary" : {
      "attachments" : 0,
      "steps" : 0
    },
    "status" : "PASSED",
    "attachments" : [ ],
    "steps" : [ ]
  }, {
    "name" : "logStep[Expected lang value : en]",
    "title" : "Expected lang value : en",
    "time" : {
      "start" : 1590514037332,
      "stop" : 1590514037332,
      "duration" : 0
    },
    "summary" : {
      "attachments" : 0,
      "steps" : 0
    },
    "status" : "PASSED",
    "attachments" : [ ],
    "steps" : [ ]
  }, {
    "name" : "logStep[PubAd lang value : en]",
    "title" : "PubAd lang value : en",
    "time" : {
      "start" : 1590514037332,
      "stop" : 1590514037332,
      "duration" : 0
    },
    "summary" : {
      "attachments" : 0,
      "steps" : 0
    },
    "status" : "PASSED",
    "attachments" : [ ],
    "steps" : [ ]
  }, {
    "name" : "logStep[lang value is matched with : en====en]",
    "title" : "lang value is matched with : en====en",
    "time" : {
      "start" : 1590514037332,
      "stop" : 1590514037332,
      "duration" : 0
    },
    "summary" : {
      "attachments" : 0,
      "steps" : 0
    },
    "status" : "PASSED",
    "attachments" : [ ],
    "steps" : [ ]
  }, {
    "name" : "logStep[Result Pass]",
    "title" : "Result Pass",
    "time" : {
      "start" : 1590514037332,
      "stop" : 1590514037332,
      "duration" : 0
    },
    "summary" : {
      "attachments" : 0,
      "steps" : 0
    },
    "status" : "PASSED",
    "attachments" : [ ],
    "steps" : [ ]
  }, {
    "name" : "logStep[Verifing :iu=%2F7646%2Fapp_android_us%2Fdb_display%2Fcard%2Flifestyle Pub Ad Call custParamlang]",
    "title" : "Verifing :iu=%2F7646%2Fapp_android_us%2Fdb_display%2Fcard%2Flifestyle Pub Ad Call custParamlang",
    "time" : {
      "start" : 1590514037486,
      "stop" : 1590514037486,
      "duration" : 0
    },
    "summary" : {
      "attachments" : 0,
      "steps" : 0
    },
    "status" : "PASSED",
    "attachments" : [ ],
    "steps" : [ ]
  }, {
    "name" : "logStep[Expected lang value : en]",
    "title" : "Expected lang value : en",
    "time" : {
      "start" : 1590514037597,
      "stop" : 1590514037597,
      "duration" : 0
    },
    "summary" : {
      "attachments" : 0,
      "steps" : 0
    },
    "status" : "PASSED",
    "attachments" : [ ],
    "steps" : [ ]
  }, {
    "name" : "logStep[PubAd lang value : en]",
    "title" : "PubAd lang value : en",
    "time" : {
      "start" : 1590514037597,
      "stop" : 1590514037597,
      "duration" : 0
    },
    "summary" : {
      "attachments" : 0,
      "steps" : 0
    },
    "status" : "PASSED",
    "attachments" : [ ],
    "steps" : [ ]
  }, {
    "name" : "logStep[lang value is matched with : en====en]",
    "title" : "lang value is matched with : en====en",
    "time" : {
      "start" : 1590514037598,
      "stop" : 1590514037598,
      "duration" : 0
    },
    "summary" : {
      "attachments" : 0,
      "steps" : 0
    },
    "status" : "PASSED",
    "attachments" : [ ],
    "steps" : [ ]
  }, {
    "name" : "logStep[Result Pass]",
    "title" : "Result Pass",
    "time" : {
      "start" : 1590514037598,
      "stop" : 1590514037598,
      "duration" : 0
    },
    "summary" : {
      "attachments" : 0,
      "steps" : 0
    },
    "status" : "PASSED",
    "attachments" : [ ],
    "steps" : [ ]
  }, {
    "name" : "logStep[Verifing :iu=%2F7646%2Fapp_android_us%2Fdb_display%2Fcard%2Fseason Pub Ad Call custParamlang]",
    "title" : "Verifing :iu=%2F7646%2Fapp_android_us%2Fdb_display%2Fcard%2Fseason Pub Ad Call custParamlang",
    "time" : {
      "start" : 1590514037738,
      "stop" : 1590514037738,
      "duration" : 0
    },
    "summary" : {
      "attachments" : 0,
      "steps" : 0
    },
    "status" : "PASSED",
    "attachments" : [ ],
    "steps" : [ ]
  }, {
    "name" : "logStep[Expected lang value : en]",
    "title" : "Expected lang value : en",
    "time" : {
      "start" : 1590514037863,
      "stop" : 1590514037863,
      "duration" : 0
    },
    "summary" : {
      "attachments" : 0,
      "steps" : 0
    },
    "status" : "PASSED",
    "attachments" : [ ],
    "steps" : [ ]
  }, {
    "name" : "logStep[PubAd lang value : en]",
    "title" : "PubAd lang value : en",
    "time" : {
      "start" : 1590514037863,
      "stop" : 1590514037863,
      "duration" : 0
    },
    "summary" : {
      "attachments" : 0,
      "steps" : 0
    },
    "status" : "PASSED",
    "attachments" : [ ],
    "steps" : [ ]
  }, {
    "name" : "logStep[lang value is matched with : en====en]",
    "title" : "lang value is matched with : en====en",
    "time" : {
      "start" : 1590514037863,
      "stop" : 1590514037863,
      "duration" : 0
    },
    "summary" : {
      "attachments" : 0,
      "steps" : 0
    },
    "status" : "PASSED",
    "attachments" : [ ],
    "steps" : [ ]
  }, {
    "name" : "logStep[Result Pass]",
    "title" : "Result Pass",
    "time" : {
      "start" : 1590514037863,
      "stop" : 1590514037863,
      "duration" : 0
    },
    "summary" : {
      "attachments" : 0,
      "steps" : 0
    },
    "status" : "PASSED",
    "attachments" : [ ],
    "steps" : [ ]
  }, {
    "name" : "logStep[Verifing :iu=%2F7646%2Fapp_android_us%2Fdb_display%2Fcard%2Faq Pub Ad Call custParamlang]",
    "title" : "Verifing :iu=%2F7646%2Fapp_android_us%2Fdb_display%2Fcard%2Faq Pub Ad Call custParamlang",
    "time" : {
      "start" : 1590514038050,
      "stop" : 1590514038050,
      "duration" : 0
    },
    "summary" : {
      "attachments" : 0,
      "steps" : 0
    },
    "status" : "PASSED",
    "attachments" : [ ],
    "steps" : [ ]
  }, {
    "name" : "logStep[Expected lang value : en]",
    "title" : "Expected lang value : en",
    "time" : {
      "start" : 1590514038184,
      "stop" : 1590514038184,
      "duration" : 0
    },
    "summary" : {
      "attachments" : 0,
      "steps" : 0
    },
    "status" : "PASSED",
    "attachments" : [ ],
    "steps" : [ ]
  }, {
    "name" : "logStep[PubAd lang value : en]",
    "title" : "PubAd lang value : en",
    "time" : {
      "start" : 1590514038184,
      "stop" : 1590514038184,
      "duration" : 0
    },
    "summary" : {
      "attachments" : 0,
      "steps" : 0
    },
    "status" : "PASSED",
    "attachments" : [ ],
    "steps" : [ ]
  }, {
    "name" : "logStep[lang value is matched with : en====en]",
    "title" : "lang value is matched with : en====en",
    "time" : {
      "start" : 1590514038184,
      "stop" : 1590514038184,
      "duration" : 0
    },
    "summary" : {
      "attachments" : 0,
      "steps" : 0
    },
    "status" : "PASSED",
    "attachments" : [ ],
    "steps" : [ ]
  }, {
    "name" : "logStep[Result Pass]",
    "title" : "Result Pass",
    "time" : {
      "start" : 1590514038185,
      "stop" : 1590514038185,
      "duration" : 0
    },
    "summary" : {
      "attachments" : 0,
      "steps" : 0
    },
    "status" : "PASSED",
    "attachments" : [ ],
    "steps" : [ ]
  }, {
    "name" : "logStep[Verifing :iu=%2F7646%2Fapp_android_us%2Fdb_display%2Fdetails%2Fmaps Pub Ad Call custParamlang]",
    "title" : "Verifing :iu=%2F7646%2Fapp_android_us%2Fdb_display%2Fdetails%2Fmaps Pub Ad Call custParamlang",
    "time" : {
      "start" : 1590514038856,
      "stop" : 1590514038856,
      "duration" : 0
    },
    "summary" : {
      "attachments" : 0,
      "steps" : 0
    },
    "status" : "PASSED",
    "attachments" : [ ],
    "steps" : [ ]
  }, {
    "name" : "logStep[Expected lang value : en]",
    "title" : "Expected lang value : en",
    "time" : {
      "start" : 1590514039482,
      "stop" : 1590514039482,
      "duration" : 0
    },
    "summary" : {
      "attachments" : 0,
      "steps" : 0
    },
    "status" : "PASSED",
    "attachments" : [ ],
    "steps" : [ ]
  }, {
    "name" : "logStep[PubAd lang value : en]",
    "title" : "PubAd lang value : en",
    "time" : {
      "start" : 1590514039482,
      "stop" : 1590514039482,
      "duration" : 0
    },
    "summary" : {
      "attachments" : 0,
      "steps" : 0
    },
    "status" : "PASSED",
    "attachments" : [ ],
    "steps" : [ ]
  }, {
    "name" : "logStep[lang value is matched with : en====en]",
    "title" : "lang value is matched with : en====en",
    "time" : {
      "start" : 1590514039482,
      "stop" : 1590514039482,
      "duration" : 0
    },
    "summary" : {
      "attachments" : 0,
      "steps" : 0
    },
    "status" : "PASSED",
    "attachments" : [ ],
    "steps" : [ ]
  }, {
    "name" : "logStep[Result Pass]",
    "title" : "Result Pass",
    "time" : {
      "start" : 1590514039482,
      "stop" : 1590514039482,
      "duration" : 0
    },
    "summary" : {
      "attachments" : 0,
      "steps" : 0
    },
    "status" : "PASSED",
    "attachments" : [ ],
    "steps" : [ ]
  }, {
    "name" : "logStep[Verifing :iu=%2F7646%2Fapp_android_us%2Fdb_display%2Fdetails%2Ftoday Pub Ad Call custParamlang]",
    "title" : "Verifing :iu=%2F7646%2Fapp_android_us%2Fdb_display%2Fdetails%2Ftoday Pub Ad Call custParamlang",
    "time" : {
      "start" : 1590514039682,
      "stop" : 1590514039682,
      "duration" : 0
    },
    "summary" : {
      "attachments" : 0,
      "steps" : 0
    },
    "status" : "PASSED",
    "attachments" : [ ],
    "steps" : [ ]
  }, {
    "name" : "logStep[Expected lang value : en]",
    "title" : "Expected lang value : en",
    "time" : {
      "start" : 1590514039834,
      "stop" : 1590514039834,
      "duration" : 0
    },
    "summary" : {
      "attachments" : 0,
      "steps" : 0
    },
    "status" : "PASSED",
    "attachments" : [ ],
    "steps" : [ ]
  }, {
    "name" : "logStep[PubAd lang value : en]",
    "title" : "PubAd lang value : en",
    "time" : {
      "start" : 1590514039834,
      "stop" : 1590514039834,
      "duration" : 0
    },
    "summary" : {
      "attachments" : 0,
      "steps" : 0
    },
    "status" : "PASSED",
    "attachments" : [ ],
    "steps" : [ ]
  }, {
    "name" : "logStep[lang value is matched with : en====en]",
    "title" : "lang value is matched with : en====en",
    "time" : {
      "start" : 1590514039834,
      "stop" : 1590514039834,
      "duration" : 0
    },
    "summary" : {
      "attachments" : 0,
      "steps" : 0
    },
    "status" : "PASSED",
    "attachments" : [ ],
    "steps" : [ ]
  }, {
    "name" : "logStep[Result Pass]",
    "title" : "Result Pass",
    "time" : {
      "start" : 1590514039834,
      "stop" : 1590514039834,
      "duration" : 0
    },
    "summary" : {
      "attachments" : 0,
      "steps" : 0
    },
    "status" : "PASSED",
    "attachments" : [ ],
    "steps" : [ ]
  }, {
    "name" : "logStep[Verifing :iu=%2F7646%2Fapp_android_us%2Fdb_display%2Fdetails%2Fhourly Pub Ad Call custParamlang]",
    "title" : "Verifing :iu=%2F7646%2Fapp_android_us%2Fdb_display%2Fdetails%2Fhourly Pub Ad Call custParamlang",
    "time" : {
      "start" : 1590514039934,
      "stop" : 1590514039934,
      "duration" : 0
    },
    "summary" : {
      "attachments" : 0,
      "steps" : 0
    },
    "status" : "PASSED",
    "attachments" : [ ],
    "steps" : [ ]
  }, {
    "name" : "logStep[Expected lang value : en]",
    "title" : "Expected lang value : en",
    "time" : {
      "start" : 1590514039995,
      "stop" : 1590514039995,
      "duration" : 0
    },
    "summary" : {
      "attachments" : 0,
      "steps" : 0
    },
    "status" : "PASSED",
    "attachments" : [ ],
    "steps" : [ ]
  }, {
    "name" : "logStep[PubAd lang value : en]",
    "title" : "PubAd lang value : en",
    "time" : {
      "start" : 1590514039995,
      "stop" : 1590514039995,
      "duration" : 0
    },
    "summary" : {
      "attachments" : 0,
      "steps" : 0
    },
    "status" : "PASSED",
    "attachments" : [ ],
    "steps" : [ ]
  }, {
    "name" : "logStep[lang value is matched with : en====en]",
    "title" : "lang value is matched with : en====en",
    "time" : {
      "start" : 1590514039995,
      "stop" : 1590514039995,
      "duration" : 0
    },
    "summary" : {
      "attachments" : 0,
      "steps" : 0
    },
    "status" : "PASSED",
    "attachments" : [ ],
    "steps" : [ ]
  }, {
    "name" : "logStep[Result Pass]",
    "title" : "Result Pass",
    "time" : {
      "start" : 1590514039995,
      "stop" : 1590514039995,
      "duration" : 0
    },
    "summary" : {
      "attachments" : 0,
      "steps" : 0
    },
    "status" : "PASSED",
    "attachments" : [ ],
    "steps" : [ ]
  }, {
    "name" : "logStep[Verifing :iu=%2F7646%2Fapp_android_us%2Fdb_display%2Fdetails%2F10day Pub Ad Call custParamlang]",
    "title" : "Verifing :iu=%2F7646%2Fapp_android_us%2Fdb_display%2Fdetails%2F10day Pub Ad Call custParamlang",
    "time" : {
      "start" : 1590514040088,
      "stop" : 1590514040088,
      "duration" : 0
    },
    "summary" : {
      "attachments" : 0,
      "steps" : 0
    },
    "status" : "PASSED",
    "attachments" : [ ],
    "steps" : [ ]
  }, {
    "name" : "logStep[Expected lang value : en]",
    "title" : "Expected lang value : en",
    "time" : {
      "start" : 1590514040145,
      "stop" : 1590514040145,
      "duration" : 0
    },
    "summary" : {
      "attachments" : 0,
      "steps" : 0
    },
    "status" : "PASSED",
    "attachments" : [ ],
    "steps" : [ ]
  }, {
    "name" : "logStep[PubAd lang value : en]",
    "title" : "PubAd lang value : en",
    "time" : {
      "start" : 1590514040145,
      "stop" : 1590514040145,
      "duration" : 0
    },
    "summary" : {
      "attachments" : 0,
      "steps" : 0
    },
    "status" : "PASSED",
    "attachments" : [ ],
    "steps" : [ ]
  }, {
    "name" : "logStep[lang value is matched with : en====en]",
    "title" : "lang value is matched with : en====en",
    "time" : {
      "start" : 1590514040145,
      "stop" : 1590514040145,
      "duration" : 0
    },
    "summary" : {
      "attachments" : 0,
      "steps" : 0
    },
    "status" : "PASSED",
    "attachments" : [ ],
    "steps" : [ ]
  }, {
    "name" : "logStep[Result Pass]",
    "title" : "Result Pass",
    "time" : {
      "start" : 1590514040145,
      "stop" : 1590514040145,
      "duration" : 0
    },
    "summary" : {
      "attachments" : 0,
      "steps" : 0
    },
    "status" : "PASSED",
    "attachments" : [ ],
    "steps" : [ ]
  } ],
  "attachments" : [ ],
  "issues" : [ ],
  "testIds" : [ ],
  "labels" : [ {
    "name" : "testSuite",
    "value" : "Suite"
  }, {
    "name" : "language",
    "value" : "JAVA"
  }, {
    "name" : "testGroup",
    "value" : "Test"
  }, {
    "name" : "testClass",
    "value" : "twc.Regression.TestCases.regressionTestCases"
  }, {
    "name" : "suite-name",
    "value" : "Suite : Test"
  }, {
    "name" : "testMethod",
    "value" : "C658711_Verify_cust_param_lang"
  }, {
    "name" : "thread",
    "value" : "3756@Aswinikumars-MacBook-Pro.local.main(1)"
  }, {
    "name" : "framework",
    "value" : "TestNG"
  }, {
    "name" : "host",
    "value" : "Aswinikumars-MacBook-Pro.local"
  }, {
    "name" : "suite-title",
    "value" : "Suite : Test"
  } ],
  "parameters" : [ ]
}